{"chunk_definitions":[{"row":9,"row_count":1,"visible":true,"expansion_state":0,"options":{"engine":"r","label":"setup","include":false,"dev":"png"},"document_id":"FAAA5901","chunk_id":"csetup_chunk","chunk_label":"setup"},{"row":68,"row_count":1,"visible":true,"expansion_state":0,"options":{"engine":"r","label":"setup environment and load traits","include":false,"warning":false,"message":false,"dev":"png"},"document_id":"FAAA5901","chunk_id":"cn8mhy7jym6i5","chunk_label":"setup environment and load traits"},{"row":351,"row_count":1,"visible":true,"expansion_state":0,"options":{"engine":"r","label":"set up phytoplankton traits","include":false,"message":false,"warning":false,"dev":"png"},"document_id":"FAAA5901","chunk_id":"c4otniummdfiv","chunk_label":"set up phytoplankton traits"},{"row":417,"row_count":1,"visible":true,"expansion_state":0,"options":{"engine":"r","label":"run models for experiment 1","include":false,"message":false,"warning":false,"dev":"png"},"document_id":"FAAA5901","chunk_id":"c5b1t8nsuwa0o","chunk_label":"run models for experiment 1"},{"row":479,"row_count":1,"visible":true,"expansion_state":0,"options":{"engine":"r","label":"run models for experiment 2","include":false,"message":false,"warning":false,"dev":"png"},"document_id":"4CEBD889","chunk_id":"chaxfhfu89n4l","chunk_label":"run models for experiment 2"},{"row":661,"row_count":1,"visible":true,"expansion_state":0,"options":{"engine":"r","label":"plot output for experiment 1","echo":false,"message":false,"warning":false,"fig.height":5,"fig.width":10,"dev":"png"},"document_id":"4CEBD889","chunk_id":"c4hzw7cylvzx2","chunk_label":"plot output for experiment 1"}],"doc_write_time":1724180356,"chunk_rendered_width":659}